aioridwell/__init__.py
aioridwell/client.py
aioridwell/const.py
aioridwell/errors.py
aioridwell/model.py
aioridwell/py.typed
aioridwell/query.py
aioridwell-2025.9.0.dist-info/METADATA
aioridwell-2025.9.0.dist-info/WHEEL
aioridwell-2025.9.0.dist-info/licenses/LICENSE
aioridwell-2025.9.0.dist-info/RECORD
