Metadata-Version: 2.4
Name: aioridwell
Version: 2025.9.0
Summary: A Python3, asyncio-based API for interacting with Ridwell waste recycling
License: MIT
License-File: LICENSE
Author: Aaron Bach
Author-email: bachya1208@gmail.com
Requires-Python: >=3.10,<4.0
Classifier: License :: OSI Approved :: MIT License
Classifier: Programming Language :: Python
Classifier: Programming Language :: Python :: 3
Classifier: Programming Language :: Python :: 3.10
Classifier: Programming Language :: Python :: 3.11
Classifier: Programming Language :: Python :: 3.12
Classifier: Programming Language :: Python :: 3.13
Classifier: Programming Language :: Python :: 3.14
Classifier: Programming Language :: Python :: Implementation :: CPython
Classifier: Programming Language :: Python :: Implementation :: PyPy
Requires-Dist: PyJWT (>=2.4.0)
Requires-Dist: aiohttp (>=3.9.0b0)
Requires-Dist: certifi (>=2023.07.22)
Requires-Dist: titlecase (>=2.3,<3.0)
Requires-Dist: yarl (>=1.9.2)
Project-URL: Bug Tracker, https://github.com/bachya/aioridwell/issues
Project-URL: Changelog, https://github.com/bachya/aioridwell/releases
Project-URL: Repository, https://github.com/bachya/aioridwell
